uquant/__init__.py
uquant/__version__.py
uquant/_typing.py
uquant/core.py
uquant-0.0.0.dist-info/LICENSE
uquant-0.0.0.dist-info/METADATA
uquant-0.0.0.dist-info/WHEEL
uquant-0.0.0.dist-info/top_level.txt
uquant-0.0.0.dist-info/RECORD
